[
  {
    "id": 10270250,
    "name": "react",
    "full_name": "react/react",
    "html_url": "https://github.com/react/react",
    "description": "The library for web and native user interfaces.",
    "stargazers_count": 246569,
    "forks_count": 51255,
    "watchers_count": 246569,
    "subscribers_count": 6599,
    "open_issues_count": 1214,
    "language": "JavaScript",
    "updated_at": "2026-07-19T04:18:58Z",
    "score": 0.9075
  },
  {
    "id": 2126244,
    "name": "bootstrap",
    "full_name": "twbs/bootstrap",
    "html_url": "https://github.com/twbs/bootstrap",
    "description": "The most popular HTML, CSS, and JavaScript framework for developing responsive, mobile first projects on the web.",
    "stargazers_count": 174488,
    "forks_count": 78725,
    "watchers_count": 174488,
    "subscribers_count": 6621,
    "open_issues_count": 275,
    "language": "MDX",
    "updated_at": "2026-07-19T03:59:51Z",
    "score": 0.76635
  },
  {
    "id": 11730342,
    "name": "vue",
    "full_name": "vuejs/vue",
    "html_url": "https://github.com/vuejs/vue",
    "description": "This is the repo for Vue 2. For Vue 3, go to https://github.com/vuejs/core",
    "stargazers_count": 210106,
    "forks_count": 33832,
    "watchers_count": 210106,
    "subscribers_count": 5766,
    "open_issues_count": 636,
    "language": "TypeScript",
    "updated_at": "2026-07-19T01:27:30Z",
    "score": 0.7123
  },
  {
    "id": 24195339,
    "name": "angular",
    "full_name": "angular/angular",
    "html_url": "https://github.com/angular/angular",
    "description": "Deliver web apps with confidence 🚀",
    "stargazers_count": 100592,
    "forks_count": 27441,
    "watchers_count": 100592,
    "subscribers_count": 3002,
    "open_issues_count": 1156,
    "language": "TypeScript",
    "updated_at": "2026-07-19T04:35:53Z",
    "score": 0.37315
  },
  {
    "id": 74293321,
    "name": "svelte",
    "full_name": "sveltejs/svelte",
    "html_url": "https://github.com/sveltejs/svelte",
    "description": "web development for the rest of us",
    "stargazers_count": 87623,
    "forks_count": 5042,
    "watchers_count": 87623,
    "subscribers_count": 911,
    "open_issues_count": 1088,
    "language": "JavaScript",
    "updated_at": "2026-07-19T04:36:55Z",
    "score": 0.22491
  },
  {
    "id": 106017343,
    "name": "tailwindcss",
    "full_name": "tailwindlabs/tailwindcss",
    "html_url": "https://github.com/tailwindlabs/tailwindcss",
    "description": "A utility-first CSS framework for rapid UI development.",
    "stargazers_count": 95980,
    "forks_count": 5401,
    "watchers_count": 95980,
    "subscribers_count": 722,
    "open_issues_count": 57,
    "language": "TypeScript",
    "updated_at": "2026-07-18T22:57:40Z",
    "score": 0.20074
  },
  {
    "id": 167174,
    "name": "jquery",
    "full_name": "jquery/jquery",
    "html_url": "https://github.com/jquery/jquery",
    "description": "jQuery JavaScript Library",
    "stargazers_count": 59806,
    "forks_count": 20393,
    "watchers_count": 59806,
    "subscribers_count": 3104,
    "open_issues_count": 118,
    "language": "JavaScript",
    "updated_at": "2026-07-18T22:28:36Z",
    "score": 0.19714
  },
  {
    "id": 3678731,
    "name": "webpack",
    "full_name": "webpack/webpack",
    "html_url": "https://github.com/webpack/webpack",
    "description": "A bundler for javascript and friends. Packs many modules into a few bundled assets. Code Splitting allows for loading parts of the application on demand. Through \"loaders\", modules can be CommonJs, AMD, ES6 modules, CSS, Images, JSON, Coffeescript, LESS, ... and your custom stuff.",
    "stargazers_count": 65844,
    "forks_count": 9409,
    "watchers_count": 65844,
    "subscribers_count": 1457,
    "open_issues_count": 145,
    "language": "JavaScript",
    "updated_at": "2026-07-19T01:53:38Z",
    "score": 0.14972
  },
  {
    "id": 71995937,
    "name": "nuxt",
    "full_name": "nuxt/nuxt",
    "html_url": "https://github.com/nuxt/nuxt",
    "description": "the full-stack Vue framework",
    "stargazers_count": 60640,
    "forks_count": 5739,
    "watchers_count": 60640,
    "subscribers_count": 796,
    "open_issues_count": 684,
    "language": "TypeScript",
    "updated_at": "2026-07-19T04:47:58Z",
    "score": 0.13556
  },
  {
    "id": 1801829,
    "name": "ember.js",
    "full_name": "emberjs/ember.js",
    "html_url": "https://github.com/emberjs/ember.js",
    "description": "Ember.js - A JavaScript framework for creating ambitious web applications",
    "stargazers_count": 22568,
    "forks_count": 4179,
    "watchers_count": 22568,
    "subscribers_count": 807,
    "open_issues_count": 333,
    "language": "TypeScript",
    "updated_at": "2026-07-18T17:22:19Z",
    "score": 0.01337
  }
]