[
  {
    "id": 31792824,
    "name": "flutter",
    "full_name": "flutter/flutter",
    "html_url": "https://github.com/flutter/flutter",
    "description": "Flutter makes it easy and fast to build beautiful apps for mobile and beyond",
    "stargazers_count": 170162,
    "forks_count": 28483,
    "watchers_count": 170162,
    "subscribers_count": 3501,
    "open_issues_count": 13167,
    "language": "Dart",
    "updated_at": "2025-05-10T22:50:33Z",
    "score": 0.99772
  },
  {
    "id": 29028775,
    "name": "react-native",
    "full_name": "facebook/react-native",
    "html_url": "https://github.com/facebook/react-native",
    "description": "A framework for building native applications using React",
    "stargazers_count": 121902,
    "forks_count": 24636,
    "watchers_count": 121902,
    "subscribers_count": 3582,
    "open_issues_count": 958,
    "language": "C++",
    "updated_at": "2025-05-11T03:04:56Z",
    "score": 0.74875
  },
  {
    "id": 12256376,
    "name": "ionic-framework",
    "full_name": "ionic-team/ionic-framework",
    "html_url": "https://github.com/ionic-team/ionic-framework",
    "description": "A powerful cross-platform UI toolkit for building native-quality iOS, Android, and Progressive Web Apps with HTML, CSS, and JavaScript.",
    "stargazers_count": 51700,
    "forks_count": 13466,
    "watchers_count": 51700,
    "subscribers_count": 1585,
    "open_issues_count": 568,
    "language": "TypeScript",
    "updated_at": "2025-05-11T01:10:38Z",
    "score": 0.34417
  },
  {
    "id": 262395224,
    "name": "maui",
    "full_name": "dotnet/maui",
    "html_url": "https://github.com/dotnet/maui",
    "description": ".NET MAUI is the .NET Multi-platform App UI, a framework for building native device applications spanning mobile, tablet, and desktop.",
    "stargazers_count": 22644,
    "forks_count": 1827,
    "watchers_count": 22644,
    "subscribers_count": 635,
    "open_issues_count": 4234,
    "language": "C#",
    "updated_at": "2025-05-10T12:38:26Z",
    "score": 0.12611
  },
  {
    "id": 31492490,
    "name": "NativeScript",
    "full_name": "NativeScript/NativeScript",
    "html_url": "https://github.com/NativeScript/NativeScript",
    "description": "⚡ Empowering JavaScript with native platform APIs. ✨ Best of all worlds (TypeScript, Swift, Objective C, Kotlin, Java, Dart). Use what you love ❤️ Angular, React, Solid, Svelte, Vue with: iOS (UIKit, SwiftUI), Android (View, Jetpack Compose), Dart (Flutter) and you name it compatible.",
    "stargazers_count": 24757,
    "forks_count": 1657,
    "watchers_count": 24757,
    "subscribers_count": 655,
    "open_issues_count": 909,
    "language": "TypeScript",
    "updated_at": "2025-05-11T02:33:02Z",
    "score": 0.11998
  },
  {
    "id": 111241370,
    "name": "capacitor",
    "full_name": "ionic-team/capacitor",
    "html_url": "https://github.com/ionic-team/capacitor",
    "description": "Build cross-platform Native Progressive Web Apps for iOS, Android, and the Web ⚡️",
    "stargazers_count": 13217,
    "forks_count": 1058,
    "watchers_count": 13217,
    "subscribers_count": 168,
    "open_issues_count": 224,
    "language": "TypeScript",
    "updated_at": "2025-05-10T14:24:23Z",
    "score": 0.05751
  },
  {
    "id": 121366401,
    "name": "cordova",
    "full_name": "apache/cordova",
    "html_url": "https://github.com/apache/cordova",
    "description": "Apache Cordova",
    "stargazers_count": 656,
    "forks_count": 69,
    "watchers_count": 656,
    "subscribers_count": 36,
    "open_issues_count": 60,
    "language": "",
    "updated_at": "2025-04-26T08:55:55Z",
    "score": 0
  }
]