[
  {
    "id": 27193779,
    "name": "node",
    "full_name": "nodejs/node",
    "html_url": "https://github.com/nodejs/node",
    "description": "Node.js JavaScript runtime ✨🐢🚀✨",
    "stargazers_count": 115112,
    "forks_count": 34302,
    "watchers_count": 115112,
    "subscribers_count": 2970,
    "open_issues_count": 2422,
    "language": "JavaScript",
    "updated_at": "2026-01-09T23:41:17Z",
    "score": 0.96012
  },
  {
    "id": 724712,
    "name": "rust",
    "full_name": "rust-lang/rust",
    "html_url": "https://github.com/rust-lang/rust",
    "description": "Empowering everyone to build reliable and efficient software.",
    "stargazers_count": 109237,
    "forks_count": 14296,
    "watchers_count": 109237,
    "subscribers_count": 1473,
    "open_issues_count": 11966,
    "language": "Rust",
    "updated_at": "2026-01-10T01:28:38Z",
    "score": 0.77314
  },
  {
    "id": 20929025,
    "name": "TypeScript",
    "full_name": "microsoft/TypeScript",
    "html_url": "https://github.com/microsoft/TypeScript",
    "description": "TypeScript is a superset of JavaScript that compiles to clean JavaScript output.",
    "stargazers_count": 107384,
    "forks_count": 13203,
    "watchers_count": 107384,
    "subscribers_count": 2156,
    "open_issues_count": 5457,
    "language": "TypeScript",
    "updated_at": "2026-01-10T02:37:24Z",
    "score": 0.75133
  },
  {
    "id": 81598961,
    "name": "cpython",
    "full_name": "python/cpython",
    "html_url": "https://github.com/python/cpython",
    "description": "The Python programming language",
    "stargazers_count": 71001,
    "forks_count": 33859,
    "watchers_count": 71001,
    "subscribers_count": 1534,
    "open_issues_count": 9225,
    "language": "Python",
    "updated_at": "2026-01-10T02:09:32Z",
    "score": 0.70703
  },
  {
    "id": 44838949,
    "name": "swift",
    "full_name": "swiftlang/swift",
    "html_url": "https://github.com/swiftlang/swift",
    "description": "The Swift Programming Language",
    "stargazers_count": 69540,
    "forks_count": 10639,
    "watchers_count": 69540,
    "subscribers_count": 2414,
    "open_issues_count": 8573,
    "language": "C++",
    "updated_at": "2026-01-10T02:38:08Z",
    "score": 0.55709
  },
  {
    "id": 3432266,
    "name": "kotlin",
    "full_name": "JetBrains/kotlin",
    "html_url": "https://github.com/JetBrains/kotlin",
    "description": "The Kotlin Programming Language. ",
    "stargazers_count": 52131,
    "forks_count": 6177,
    "watchers_count": 52131,
    "subscribers_count": 1518,
    "open_issues_count": 206,
    "language": "Kotlin",
    "updated_at": "2026-01-09T23:41:46Z",
    "score": 0.36869
  },
  {
    "id": 1903522,
    "name": "php-src",
    "full_name": "php/php-src",
    "html_url": "https://github.com/php/php-src",
    "description": "The PHP Interpreter",
    "stargazers_count": 39761,
    "forks_count": 7987,
    "watchers_count": 39761,
    "subscribers_count": 1354,
    "open_issues_count": 1689,
    "language": "C",
    "updated_at": "2026-01-10T01:16:15Z",
    "score": 0.31808
  },
  {
    "id": 538746,
    "name": "ruby",
    "full_name": "ruby/ruby",
    "html_url": "https://github.com/ruby/ruby",
    "description": "The Ruby Programming Language",
    "stargazers_count": 23254,
    "forks_count": 5547,
    "watchers_count": 23254,
    "subscribers_count": 1065,
    "open_issues_count": 529,
    "language": "Ruby",
    "updated_at": "2026-01-10T02:30:26Z",
    "score": 0.19968
  },
  {
    "id": 149121954,
    "name": "jdk",
    "full_name": "openjdk/jdk",
    "html_url": "https://github.com/openjdk/jdk",
    "description": "JDK main-line development https://openjdk.org/projects/jdk",
    "stargazers_count": 22341,
    "forks_count": 6219,
    "watchers_count": 22341,
    "subscribers_count": 361,
    "open_issues_count": 386,
    "language": "Java",
    "updated_at": "2026-01-10T03:13:07Z",
    "score": 0.17551
  },
  {
    "id": 35726310,
    "name": "sdk",
    "full_name": "dart-lang/sdk",
    "html_url": "https://github.com/dart-lang/sdk",
    "description": "The Dart SDK, including the VM, JS and Wasm compilers, analysis, core libraries, and more.",
    "stargazers_count": 10990,
    "forks_count": 1727,
    "watchers_count": 10990,
    "subscribers_count": 287,
    "open_issues_count": 8289,
    "language": "Dart",
    "updated_at": "2026-01-10T01:44:57Z",
    "score": 0.11413
  },
  {
    "id": 4072305,
    "name": "compiler",
    "full_name": "elm/compiler",
    "html_url": "https://github.com/elm/compiler",
    "description": "Compiler for Elm, a functional language for reliable webapps.",
    "stargazers_count": 7734,
    "forks_count": 672,
    "watchers_count": 7734,
    "subscribers_count": 198,
    "open_issues_count": 337,
    "language": "Haskell",
    "updated_at": "2026-01-06T21:23:55Z",
    "score": 0.05325
  },
  {
    "id": 8183570,
    "name": "perl5",
    "full_name": "Perl/perl5",
    "html_url": "https://github.com/Perl/perl5",
    "description": "🐪 The Perl programming language",
    "stargazers_count": 2213,
    "forks_count": 605,
    "watchers_count": 2213,
    "subscribers_count": 22,
    "open_issues_count": 2408,
    "language": "Perl",
    "updated_at": "2026-01-09T19:50:28Z",
    "score": 0.02671
  },
  {
    "id": 19646830,
    "name": "go",
    "full_name": "go-lang/go",
    "html_url": "https://github.com/go-lang/go",
    "description": "Mirror of code.google.com/p/go/ ",
    "stargazers_count": 0,
    "forks_count": 1,
    "watchers_count": 0,
    "subscribers_count": 1,
    "open_issues_count": 0,
    "language": "Go",
    "updated_at": "2018-09-30T14:24:04Z",
    "score": 0
  }
]