[
  {
    "id": 27193779,
    "name": "node",
    "full_name": "nodejs/node",
    "html_url": "https://github.com/nodejs/node",
    "description": "Node.js JavaScript runtime ✨🐢🚀✨",
    "stargazers_count": 112744,
    "forks_count": 32629,
    "watchers_count": 112744,
    "subscribers_count": 2969,
    "open_issues_count": 2344,
    "language": "JavaScript",
    "updated_at": "2025-08-16T03:07:29Z",
    "score": 0.9602
  },
  {
    "id": 724712,
    "name": "rust",
    "full_name": "rust-lang/rust",
    "html_url": "https://github.com/rust-lang/rust",
    "description": "Empowering everyone to build reliable and efficient software.",
    "stargazers_count": 105810,
    "forks_count": 13651,
    "watchers_count": 105810,
    "subscribers_count": 1471,
    "open_issues_count": 11490,
    "language": "Rust",
    "updated_at": "2025-08-16T03:12:37Z",
    "score": 0.76722
  },
  {
    "id": 20929025,
    "name": "TypeScript",
    "full_name": "microsoft/TypeScript",
    "html_url": "https://github.com/microsoft/TypeScript",
    "description": "TypeScript is a superset of JavaScript that compiles to clean JavaScript output.",
    "stargazers_count": 105613,
    "forks_count": 12960,
    "watchers_count": 105613,
    "subscribers_count": 2153,
    "open_issues_count": 6056,
    "language": "TypeScript",
    "updated_at": "2025-08-15T23:19:57Z",
    "score": 0.7602
  },
  {
    "id": 81598961,
    "name": "cpython",
    "full_name": "python/cpython",
    "html_url": "https://github.com/python/cpython",
    "description": "The Python programming language",
    "stargazers_count": 68383,
    "forks_count": 32595,
    "watchers_count": 68383,
    "subscribers_count": 1525,
    "open_issues_count": 9291,
    "language": "Python",
    "updated_at": "2025-08-16T03:09:42Z",
    "score": 0.70544
  },
  {
    "id": 44838949,
    "name": "swift",
    "full_name": "swiftlang/swift",
    "html_url": "https://github.com/swiftlang/swift",
    "description": "The Swift Programming Language",
    "stargazers_count": 68957,
    "forks_count": 10519,
    "watchers_count": 68957,
    "subscribers_count": 2438,
    "open_issues_count": 8476,
    "language": "C++",
    "updated_at": "2025-08-16T02:34:52Z",
    "score": 0.56656
  },
  {
    "id": 3432266,
    "name": "kotlin",
    "full_name": "JetBrains/kotlin",
    "html_url": "https://github.com/JetBrains/kotlin",
    "description": "The Kotlin Programming Language. ",
    "stargazers_count": 51106,
    "forks_count": 5986,
    "watchers_count": 51106,
    "subscribers_count": 1528,
    "open_issues_count": 189,
    "language": "Kotlin",
    "updated_at": "2025-08-16T03:15:58Z",
    "score": 0.3701
  },
  {
    "id": 1903522,
    "name": "php-src",
    "full_name": "php/php-src",
    "html_url": "https://github.com/php/php-src",
    "description": "The PHP Interpreter",
    "stargazers_count": 39357,
    "forks_count": 7930,
    "watchers_count": 39357,
    "subscribers_count": 1371,
    "open_issues_count": 1500,
    "language": "C",
    "updated_at": "2025-08-16T02:52:21Z",
    "score": 0.32289
  },
  {
    "id": 538746,
    "name": "ruby",
    "full_name": "ruby/ruby",
    "html_url": "https://github.com/ruby/ruby",
    "description": "The Ruby Programming Language",
    "stargazers_count": 22854,
    "forks_count": 5452,
    "watchers_count": 22854,
    "subscribers_count": 1088,
    "open_issues_count": 460,
    "language": "Ruby",
    "updated_at": "2025-08-16T02:42:12Z",
    "score": 0.20202
  },
  {
    "id": 149121954,
    "name": "jdk",
    "full_name": "openjdk/jdk",
    "html_url": "https://github.com/openjdk/jdk",
    "description": "JDK main-line development https://openjdk.org/projects/jdk",
    "stargazers_count": 21509,
    "forks_count": 6148,
    "watchers_count": 21509,
    "subscribers_count": 356,
    "open_issues_count": 398,
    "language": "Java",
    "updated_at": "2025-08-16T01:43:06Z",
    "score": 0.17526
  },
  {
    "id": 35726310,
    "name": "sdk",
    "full_name": "dart-lang/sdk",
    "html_url": "https://github.com/dart-lang/sdk",
    "description": "The Dart SDK, including the VM, JS and Wasm compilers, analysis, core libraries, and more.",
    "stargazers_count": 10733,
    "forks_count": 1675,
    "watchers_count": 10733,
    "subscribers_count": 287,
    "open_issues_count": 8229,
    "language": "Dart",
    "updated_at": "2025-08-15T22:39:30Z",
    "score": 0.11539
  },
  {
    "id": 4072305,
    "name": "compiler",
    "full_name": "elm/compiler",
    "html_url": "https://github.com/elm/compiler",
    "description": "Compiler for Elm, a functional language for reliable webapps.",
    "stargazers_count": 7669,
    "forks_count": 667,
    "watchers_count": 7669,
    "subscribers_count": 203,
    "open_issues_count": 335,
    "language": "Haskell",
    "updated_at": "2025-08-13T09:39:37Z",
    "score": 0.05418
  },
  {
    "id": 8183570,
    "name": "perl5",
    "full_name": "Perl/perl5",
    "html_url": "https://github.com/Perl/perl5",
    "description": "🐪 The Perl programming language",
    "stargazers_count": 2151,
    "forks_count": 589,
    "watchers_count": 2151,
    "subscribers_count": 23,
    "open_issues_count": 2378,
    "language": "Perl",
    "updated_at": "2025-08-15T16:07:36Z",
    "score": 0.02704
  },
  {
    "id": 19646830,
    "name": "go",
    "full_name": "go-lang/go",
    "html_url": "https://github.com/go-lang/go",
    "description": "Mirror of code.google.com/p/go/ ",
    "stargazers_count": 0,
    "forks_count": 1,
    "watchers_count": 0,
    "subscribers_count": 1,
    "open_issues_count": 0,
    "language": "Go",
    "updated_at": "2018-09-30T14:24:04Z",
    "score": 0
  }
]